{
  "description": "Centralized label mappings for auto-labeling issues and pull requests based on title keywords",
  "version": "1.0.0",
  "mappings": {
    "issues": {
      "comment": "Note: Only labels that exist in the repository are included",
      "[infra]": "infrastructure",
      "[infrastructure]": "infrastructure",
      "[docs]": "documentation",
      "[documentation]": "documentation",
      "[dpdk]": "dpdk",
      "[bmv2]": "bmv2",
      "[ebpf]": "ebpf",
      "[p4testgen]": "p4tools",
      "[p4smith]": "p4tools",
      "[p4tools]": "p4tools",
      "[p4tc]": "p4tc",
      "[p4fmt]": "p4fmt",
      "[core]": "core",
      "[p4-spec]": "p4-spec",
      "[control-plane]": "control-plane",
      "[p4runtime]": "control-plane",
      "[frontend]": "core",
      "[midend]": "core",
      "[parser]": "core",
      "[python]": "python",
      "[pna-bmv2]": "pna-bmv2",
      "[psa-bmv2]": "psa-bmv2",
      "[ebpf-psa]": "ebpf-psa"
    },
    "pull_requests": {
      "comment": "Note: Only labels that exist in the repository are included",
      "[core]": "core",
      "[infra]": "infrastructure",
      "[infrastructure]": "infrastructure",
      "[midend]": "core",
      "[parser]": "core",
      "[dpdk]": "dpdk",
      "[p4-spec]": "p4-spec",
      "[bmv2]": "bmv2",
      "[docs]": "documentation",
      "[documentation]": "documentation",
      "[p4testgen]": "p4tools",
      "[p4smith]": "p4tools",
      "[p4tools]": "p4tools",
      "[control-plane]": "control-plane",
      "[p4runtime]": "control-plane",
      "[p4tc]": "p4tc",
      "[p4fmt]": "p4fmt",
      "[frontend]": "core",
      "[ebpf]": "ebpf",
      "[python]": "python",
      "[pna-bmv2]": "pna-bmv2",
      "[psa-bmv2]": "psa-bmv2",
      "[ebpf-psa]": "ebpf-psa"
    }
  },
  "notes": {
    "case_sensitivity": "All keyword matching is case-insensitive",
    "format": "Keywords should be in [brackets] format",
    "label_values": "Must match existing GitHub labels in the repository",
    "adding_labels": "To add new label mappings, first ensure the label exists in the repository, then add the mapping here",
    "excluded_labels": "The following keywords were mentioned in issue #5649 but labels don't exist: [bug], [feature]/[enhancement], [ubpf], [graphs], [tofino]. These can be added once the labels are created in the repository."
  }
}
